jirazephyrupdate/jirazephyrupdate.py
jirazephyrupdate-1.4.dist-info/LICENSE
jirazephyrupdate-1.4.dist-info/METADATA
jirazephyrupdate-1.4.dist-info/WHEEL
jirazephyrupdate-1.4.dist-info/top_level.txt
jirazephyrupdate-1.4.dist-info/RECORD
