Metadata-Version: 2.1
Name: jirazephyrupdate
Version: 1.4
Summary: Utility for zephyr jira
Home-page: https://github.com/santanuray1983/ZephyrTestResultsUpdate
Author: Santanu Ray
Author-email: santanuray1983@gmail.com
License: UNKNOWN
Platform: UNKNOWN
Classifier: Programming Language :: Python :: 3
Classifier: Programming Language :: Python :: 2
Classifier: Programming Language :: Python :: 2.7
Classifier: Programming Language :: Python :: 3.4
Classifier: Programming Language :: Python :: 3.5
Classifier: License :: OSI Approved :: MIT License
Classifier: Operating System :: OS Independent
Requires-Dist: requests
